moontorch/__init__.py
moontorch/main.py
moontorch-0.0.3.dist-info/METADATA
moontorch-0.0.3.dist-info/WHEEL
moontorch-0.0.3.dist-info/top_level.txt
moontorch-0.0.3.dist-info/RECORD
