Metadata-Version: 2.1
Name: moontorch
Version: 0.0.3
Summary: UNKNOWN
License: UNKNOWN
Platform: UNKNOWN
Requires-Dist: torch
